Metadata-Version: 2.1
Name: astpy
Version: 0.0.4
Summary: A standard library python package
Home-page: https://github.com/antonsetiazi/astpy_package
Author: Mohamad Anton Setiazi
Author-email: antons899@gmail.com
License: UNKNOWN
Platform: UNKNOWN
Classifier: Programming Language :: Python :: 3
Classifier: License :: OSI Approved :: MIT License
Classifier: Operating System :: OS Independent
Requires-Python: >=3.6
